model_confidence_set/__init__.py
model_confidence_set/core.py
model_confidence_set-0.1.3.dist-info/LICENSE
model_confidence_set-0.1.3.dist-info/METADATA
model_confidence_set-0.1.3.dist-info/WHEEL
model_confidence_set-0.1.3.dist-info/top_level.txt
model_confidence_set-0.1.3.dist-info/RECORD
