Metadata-Version: 2.1
Name: model-confidence-set
Version: 0.1.3
Summary: model-confidence-set provides a Python implementation of the Model Confidence Set (MCS) procedure (Hansen, Lunde, and Nason, 2011), a statistical method for comparing and selecting models based on their performance.
Home-page: https://github.com/JLDC/model-confidence-set
Author: Jonathan Chassot
Author-email: jonathan.chassot@unisg.ch
License: MIT
Keywords: model confidence set,model evaluation,statistical model comparison,model performance analysis,model selection,predictive accuracy,econometrics,financial econometrics
License-File: LICENSE
Requires-Dist: numba >=0.59.0
Requires-Dist: numpy >=1.26.4
Requires-Dist: pandas >=2.2.1
Requires-Dist: tqdm >=4.66.2
